scripts/__init__.py
scripts/converter_hf_to_mcore.py
scripts/diagnose.py
scripts/init_random_model.py
scripts/legacy_model_merger.py
tests/__init__.py
tests/test_base_config_on_cpu.py
tests/test_protocol_on_cpu.py
tests/interactions/__init__.py
tests/interactions/test_gsm8k_interaction.py
tests/interactions/test_interaction_registry.py
tests/single_controller/__init__.py
tests/single_controller/test_auto_padding_on_cpu.py
tests/single_controller/test_colocated_workers.py
tests/single_controller/test_colocated_workers_fused.py
tests/single_controller/test_data_transfer.py
tests/single_controller/test_decorator_on_cpu.py
tests/single_controller/test_driverfunc_to_worker.py
tests/single_controller/test_fused_workers_on_cpu.py
tests/single_controller/test_high_level_scheduling_api.py
tests/single_controller/test_ray_collectives.py
tests/single_controller/test_ray_local_envs_on_cpu.py
tests/single_controller/test_ray_utils_on_cpu.py
tests/single_controller/test_rvdz.py
tests/single_controller/test_worker_group_basics.py
tests/single_controller/test_worker_group_torch.py
tests/special_e2e/__init__.py
tests/special_e2e/check_custom_rwd_fn.py
tests/special_e2e/check_results.py
tests/special_e2e/envs/__init__.py
tests/special_e2e/envs/digit_completion/__init__.py
tests/special_e2e/envs/digit_completion/task.py
tests/special_e2e/envs/digit_completion/tokenizer.py
tests/trainer/__init__.py
tests/trainer/config/__init__.py
tests/trainer/config/test_algo_config_on_cpu.py
tests/trainer/ppo/__init__.py
tests/trainer/ppo/test_core_algos_on_cpu.py
tests/trainer/ppo/test_metric_utils_on_cpu.py
verl/__init__.py
verl/base_config.py
verl/protocol.py
verl/experimental/__init__.py
verl/experimental/agent_loop/__init__.py
verl/experimental/agent_loop/agent_loop.py
verl/experimental/agent_loop/single_turn_agent_loop.py
verl/experimental/agent_loop/tool_agent_loop.py
verl/interactions/__init__.py
verl/interactions/base.py
verl/interactions/gsm8k_interaction.py
verl_cgft-0.4.1.dev0.dist-info/licenses/LICENSE
verl_cgft-0.4.1.dev0.dist-info/METADATA
verl_cgft-0.4.1.dev0.dist-info/WHEEL
verl_cgft-0.4.1.dev0.dist-info/top_level.txt
verl_cgft-0.4.1.dev0.dist-info/RECORD
